llama_index/embeddings/huggingface_openvino/__init__.py
llama_index/embeddings/huggingface_openvino/base.py
llama_index_embeddings_openvino-0.6.1.dist-info/METADATA
llama_index_embeddings_openvino-0.6.1.dist-info/WHEEL
llama_index_embeddings_openvino-0.6.1.dist-info/licenses/LICENSE
llama_index_embeddings_openvino-0.6.1.dist-info/RECORD
