Metadata-Version: 2.4
Name: llama-index-embeddings-openvino
Version: 0.6.1
Summary: llama-index embeddings openvino integration
Author-email: Your Name <you@example.com>
License-Expression: MIT
License-File: LICENSE
Requires-Python: <4.0,>=3.9
Requires-Dist: huggingface-hub>=0.23.0
Requires-Dist: llama-index-core<0.15,>=0.13.0
Requires-Dist: llama-index-embeddings-huggingface<0.7,>=0.6.0
Requires-Dist: optimum-intel[openvino]<2,>=1.22.0
